{
    "products": [
        {
            "id": 1,
            "title": "Fjallraven - Foldsack No. 1 Backpack, Fits 15 Laptops",
            "description": "Your perfect pack for everyday use and walks in the forest. Stash your laptop (up to 15 inches) in the padded sleeve, your everyday",
            "category": "men's clothing",
            "price": 109.95,
            "rating": 3.9
        },
        {
            "id": 5,
            "title": "John Hardy Women's Legends Naga Gold & Silver Dragon Station Chain Bracelet",
            "description": "From our Legends Collection, the Naga was inspired by the mythical water dragon that protects the ocean's pearl.",
            "category": "jewelery",
            "price": 695,
            "rating": 4.6
        },
        {
            "id": 9,
            "title": "WD 2TB Elements Portable External Hard Drive - USB 3.0",
            "description": "USB 3.0 and USB 2.0 Compatibility Fast data transfers Improve PC Performance High Capacity.",
            "category": "electronics",
            "price": 64,
            "rating": 3.3
        },
        {
            "id": 15,
            "title": "BIYLACLESEN Women's 3-in-1 Snowboard Jacket Winter Coats",
            "description": "Note:The Jackets is US standard size, Please choose size as your usual wear.",
            "category": "women's clothing",
            "price": 56.99,
            "rating": 2.6
        },
        {
            "id": 21,
            "title": "Apple AirPods Pro (2nd Generation)",
            "description": "Active Noise Cancellation, Transparency mode, Adaptive EQ, and a customizable fit for all-day comfort.",
            "category": "electronics",
            "price": 249.99,
            "rating": 4.9
        },
        {
            "id": 24,
            "title": "Ray-Ban Classic Aviator Sunglasses",
            "description": "Timeless design, 100% UV protection, and durable metal frame.",
            "category": "jewelery",
            "price": 154.00,
            "rating": 4.7
        },
        {
            "id": 25,
            "title": "Levi's Women's 721 High Rise Skinny Jeans",
            "description": "Super stretch denim, high-rise fit, and classic five-pocket styling.",
            "category": "women's clothing",
            "price": 49.99,
            "rating": 4.4
        },
        {
            "id": 28,
            "title": "Apple MacBook Air M2",
            "description": "Supercharged by the Apple M2 chip, 13.6-inch Liquid Retina display, and all-day battery life.",
            "category": "electronics",
            "price": 1199.00,
            "rating": 4.9
        },
        {
            "id": 29,
            "title": "Casio Men's G-Shock Quartz Watch",
            "description": "Shock resistant, 200 meter water resistance, and LED backlight.",
            "category": "jewelery",
            "price": 99.99,
            "rating": 4.5
        },
        {
            "id": 32,
            "title": "Columbia Women's Benton Springs Fleece Jacket",
            "description": "Soft fleece, modern classic fit, and zippered hand pockets.",
            "category": "women's clothing",
            "price": 39.99,
            "rating": 4.6
        },
        {
            "id": 35,
            "title": "Under Armour Men's Tech 2.0 T-Shirt",
            "description": "Quick-drying, ultra-soft fabric with a more natural feel.",
            "category": "men's clothing",
            "price": 25.00,
            "rating": 4.7
        },
        {
            "id": 36,
            "title": "Samsung Galaxy Tab S8",
            "description": "11-inch LCD display, S Pen included, and long-lasting battery.",
            "category": "electronics",
            "price": 699.99,
            "rating": 4.8
        },
        {
            "id": 37,
            "title": "Pandora Moments Snake Chain Bracelet",
            "description": "Sterling silver, classic design, and compatible with Pandora charms.",
            "category": "jewelery",
            "price": 65.00,
            "rating": 4.5
        },
        {
            "id": 38,
            "title": "The North Face Women's Resolve 2 Jacket",
            "description": "Waterproof, breathable, and seam-sealed for outdoor adventures.",
            "category": "women's clothing",
            "price": 89.00,
            "rating": 4.7
        },
        {
            "id": 39,
            "title": "Apple Watch Series 9",
            "description": "Advanced health features, always-on Retina display, and fast charging.",
            "category": "electronics",
            "price": 399.00,
            "rating": 4.9
        }
    ]
}
